PySliders/__init__.py
PySliders/aspect_resize.py
PySliders-0.1.1.dist-info/LICENSE
PySliders-0.1.1.dist-info/METADATA
PySliders-0.1.1.dist-info/WHEEL
PySliders-0.1.1.dist-info/top_level.txt
PySliders-0.1.1.dist-info/RECORD
