Metadata-Version: 2.1
Name: PySliders
Version: 0.1.1
Summary: A sliders add-on for PyGame
Home-page: https://github.com/stshrewsburyDev/PySliders
Author: Steven Shrewsbury
Author-email: UNKNOWN
License: MIT
Platform: UNKNOWN
Requires-Dist: pygame
